Angular_Deviation_Diffuser/__init__.py
Angular_Deviation_Diffuser/extract_six_angles.py
Angular_Deviation_Diffuser/loss.py
Angular_Deviation_Diffuser/model.py
Angular_Deviation_Diffuser/reconstruct_coordinate.py
Angular_Deviation_Diffuser/refine.py
Angular_Deviation_Diffuser/sampling.py
Angular_Deviation_Diffuser/training.py
Angular_Deviation_Diffuser/util.py
Angular_Deviation_Diffuser-1.0.9.dist-info/LICENSE
Angular_Deviation_Diffuser-1.0.9.dist-info/METADATA
Angular_Deviation_Diffuser-1.0.9.dist-info/WHEEL
Angular_Deviation_Diffuser-1.0.9.dist-info/top_level.txt
Angular_Deviation_Diffuser-1.0.9.dist-info/RECORD
