Metadata-Version: 2.1
Name: Angular_Deviation_Diffuser
Version: 1.0.9
Summary: This is a Transformer-Based diffusion model for Efficient Protein Conformational Ensemble Generation
Author-email: yi yang <yiyangalan@gmail.com>
License: MIT License
Project-URL: Homepage, https://github.com/AlanYangYi/angular_deviation_diffuser
Keywords: diffusion model,protein conformation,angular deviation
Classifier: License :: OSI Approved :: MIT License
Classifier: Programming Language :: Python
Classifier: Programming Language :: Python :: 3
Classifier: Intended Audience :: Science/Research
Classifier: Topic :: Scientific/Engineering :: Bio-Informatics
Requires-Python: >=3.8
License-File: LICENSE
Requires-Dist: numpy<=1.26.4
Requires-Dist: lightning>=2.4.0
Requires-Dist: transformers>=4.20.0
Requires-Dist: biotite==0.35.0
Requires-Dist: pandas
Requires-Dist: pyrosetta-installer
